my_data/__init__.py
my_data/authenticator.py
my_data/authorizer.py
my_data/context.py
my_data/context_data.py
my_data/creators.py
my_data/data_loader.py
my_data/data_manipulator.py
my_data/deleters.py
my_data/exceptions.py
my_data/my_data.py
my_data/my_data_table_creator.py
my_data/py.typed
my_data/resource_manager.py
my_data/retrievers.py
my_data/updaters.py
my_model/__init__.py
my_model/model.py
my_model/py.typed
ds_my_data-1.2.5.dist-info/LICENSE.md
ds_my_data-1.2.5.dist-info/METADATA
ds_my_data-1.2.5.dist-info/WHEEL
ds_my_data-1.2.5.dist-info/RECORD
